Metadata-Version: 1.1
Name: pygdc
Version: 0.0.2
Summary: Python API for Genomic Data Commons
Home-page: UNKNOWN
Author: UNKNOWN
Author-email: UNKNOWN
License: http://www.apache.org/licenses/LICENSE-2.0.html
Platform: UNKNOWN
Classifier: Development Status :: 3 - Alpha
Classifier: Environment :: Console
Classifier: Operating System :: OS Independent
Classifier: Intended Audience :: Science/Research
Classifier: License :: OSI Approved :: Apache Software License
Classifier: Programming Language :: Python
Classifier: Topic :: Scientific/Engineering :: Bio-Informatics
